RandomSparseMatrix/RandomFunctions.py
RandomSparseMatrix/__init__.py
RandomSparseMatrix-0.1.0.dist-info/LICENSE
RandomSparseMatrix-0.1.0.dist-info/METADATA
RandomSparseMatrix-0.1.0.dist-info/WHEEL
RandomSparseMatrix-0.1.0.dist-info/top_level.txt
RandomSparseMatrix-0.1.0.dist-info/RECORD
