Metadata-Version: 2.1
Name: RandomSparseMatrix
Version: 0.1.0
Summary: Package for creation of sparse matrices (SSparseMatrix objects.)
Home-page: https://github.com/antononcube/Python-packages/tree/main/RandomSparseMatrix
Author: Anton Antonov
Author-email: antononcube@posteo.net
License: UNKNOWN
Keywords: sparse,matrix,r,s,s-plus,linear algebra,linear,algebra,row names,column names,named rows,named columns
Platform: UNKNOWN
Classifier: Intended Audience :: Science/Research
Classifier: Intended Audience :: Developers
Classifier: Programming Language :: Python :: 3
Classifier: License :: OSI Approved :: BSD License
Classifier: Intended Audience :: Science/Research
Classifier: Intended Audience :: Developers
Classifier: Operating System :: OS Independent
Requires-Python: >=3.7
License-File: LICENSE
Requires-Dist: SSparseMatrix
Requires-Dist: RandomDataGenerators
Requires-Dist: SparseMatrixRecommender
